{
	"id":63,
	"description":"HSC Assessment",
	"name":"hsc_assessment",
	"pages":[
	    {
	    	"name":"intro",
	    	"title":"Information",
	    	"items":[
	    	    {
	    	    	"name":"contact",
	    	    	"label":"Contact",
	    	    	"type":"TEXT",
	    	    	"value":"",
	    	    	"attributes":{"readonly":"true"}
	    	    },
	    	    {
	    	    	"name":"address",
	    	    	"label":"Address",
	    	    	"type":"TEXT",
	    	    	"value":"",
	    	    	"attributes":{"readonly":"true"}
	    	    },
	    	    {
	    	    	"name":"password",
	    	    	"label":"Password",
	    	    	"type":"TEXT",
	    	    	"value":"",
	    	    	"attributes":{"readonly":"true"}
	    	    },
	    	    {
	    	    	"name":"notes",
	    	    	"label":"Notes",
	    	    	"type":"TEXT",
	    	    	"value":"",
	    	    	"attributes":{"readonly":"true"}
	    	    }
	    	]
	    },
	    {
	    	"name":"assessment_details",
	    	"title":"Assessment Details",
	    	"items":[
	    	    {
	    	    	"name":"assessor_1",
	    	    	"label":"Assessor 1",
	    	    	"type":"TEXT",
	    	    	"value":"current_user"
	    	    },
	    	    {
	    	    	"name":"assessor_2",
	    	    	"label":"Assessor 2",
	    	    	"type":"TEXT"
	    	    }		    	    
	    	]
	    },
	    {
	    	"name":"share_details",
	    	"title":"Share Information",
	    	"items":[
	    	    {
	    	    	"name":"share_label",
	    	    	"label":"Explain to the occupier how the information gathered during this assessment can be shared with partner organisations",
	    	    	"type":"LABEL"
	    	    },
	    	    {
	    	    	"name":"share_info",
	    	    	"label":"Occupier aggrees to share?",
	    	    	"type":"YESNO"
	    	    }
	    	]
	    },
	    {
	    	"name":"property_details",
	    	"title":"Property Details",
	    	"items":[
	    	    {
	    	    	"name":"tenure_type",
	    	    	"label":"Tenure Type",
	    	    	"type":"SELECT",
	    	    	"values":[{"label":"Owner occupied","value":"owner_occupied"},
	    	    	         {"label":"Rented - Council/Housing Association","value":"rented_ha"},
	    	    	         {"label":"Rented - Private","value":"rented_private"},
	    	    	         {"label":"Rented - Landlord unknown","value":"rented_unknown"},
	    	    	         {"label":"Not known","value":"not_known"}]
	    	    },
	    	    {
	    	    	"name":"ha_id",
	    	    	"label":"Housing Association",
	    	    	"type":"TEXT"
	    	    },
	    	    {
	    	    	"name":"hmo",
	    	    	"label":"HMO?",
	    	    	"type":"YESNO"
	    	    }
	    	]
	    },
	    {
	    	"name":"occupancy",
	    	"title":"Occupancy",
	    	"items":[
	    	    {
	    	    	"name":"ethnicity",
	    	    	"label":"Ethnicity",
	    	    	"type":"SELECT",
	    	    	"values":[{"label":"British","value":"white_british"},
	    	    	         {"label":"Irish","value":"white_irish"},
	    	    	         {"label":"Gypsy or Irish Traveller","value":"white_traveller"},
	    	    	         {"label":"Any other White background","value":"white_other"},
	    	    	         {"label":"White & Black Caribbean","value":"mixed_caribbean"},
	    	    	         {"label":"White & Black African","value":"mixed_african"},
	    	    	         {"label":"White & Asian","value":"mixed_asian"},
	    	    	         {"label":"Other Mixed","value":"mixed_other"},
	    	    	         {"label":"Indian","value":"asian_indian"},
	    	    	         {"label":"Pakistani","value":"asian_pakistani"},
	    	    	         {"label":"Bangladeshi","value":"asian_bangladeshi"},
	    	    	         {"label":"Any other Asian background","value":"asian_other"},
	    	    	         {"label":"African","value":"black_african"},
	    	    	         {"label":"Caribbean","value":"black_caribbean"},
	    	    	         {"label":"Any other Black background","value":"black_other"},
	    	    	         {"label":"Arab","value":"other_arab"},
	    	    	         {"label":"Any other ethnic background","value":"other_any"}],
	    	    	"attributes":{"multiselect":"true"}
	    	    },
	    	    {
	    	    	"name":"occupancy_numbers",
	    	    	"label":"Occupancy Numbers",
	    	    	"type":"LABEL"
	    	    },
	    	    {
	    	    	"name":"occupants_0-5",
	    	    	"label":"0-5",
	    	    	"type":"NUMERIC"
	    	    },
	    	    {
	    	    	"name":"occupants_65+",
	    	    	"label":"65+",
	    	    	"type":"NUMERIC"
	    	    },
	    	    {
	    	    	"name":"occupants_other",
	    	    	"label":"Other",
	    	    	"type":"NUMERIC"
	    	    }
	    	]
	    },
	    {
	    	"name":"fire_hazards",
	    	"title":"Fire Hazards",
	    	"items":[
	    	    {
	    	    	"name":"hazard_chippan",
	    	    	"label":"Is a chip pan in use?",
	    	    	"type":"YESNO"
	    	    },
	    	    {
	    	    	"name":"hazard_blankets",
	    	    	"label":"Electric blankets in the property?",
	    	    	"type":"YESNO"
	    	    },
	    	    {
	    	    	"name":"hazard_smoker",
	    	    	"label":"Does anyone in the household smoke?",
	    	    	"type":"YESNO"
	    	    },
	    	    {
	    	    	"name":"hazard_candles",
	    	    	"label":"Are candles used inappropriately?",
	    	    	"type":"YESNO"
	    	    },
	    	    {
	    	    	"name":"hazard_clothes",
	    	    	"label":"Are clothes dried dangerously?",
	    	    	"type":"YESNO"
	    	    },
	    	    {
	    	    	"name":"hazard_sockets",
	    	    	"label":"Are plug sockets/adaptors overloaded?",
	    	    	"type":"YESNO"
	    	    }
	    	]
	    },
	    {
	    	"name":"hazard_notes",
	    	"title":"Fire Hazard Notes",
	    	"items":[
	    	    {
	    	    	"name":"fire_hazard_label",
	    	    	"label":"Please provide any further information relating to the fire hazards.",
	    	    	"type":"LABEL"
	    	    },
	    	    {
	    	    	"name":"fire_hazard_notes",
	    	    	"label":"Further information",
	    	    	"type":"TEXT"
	    	    }
	    	]
	    },
	    {
	    	"name":"individual_risks",
	    	"title":"Individual Risks",
	    	"items":[
	    	    {
	    	    	"name":"mobility_label",
	    	    	"label":"Will the occupier...",
	    	    	"type":"LABEL"
	    	    },
	    	    {
	    	    	"name":"slow_to_vacate",
	    	    	"label":"Be slow to vacate the property?",
	    	    	"type":"YESNO"
	    	    },
	    	    {
	    	    	"name":"assistance_to_vacate",
	    	    	"label":"Require assistance to vacate the property?",
	    	    	"type":"YESNO"
	    	    },
	    	    {
	    	    	"name":"techrescue_vacate",
	    	    	"label":"Require specialist tech rescue equipment?",
	    	    	"type":"YESNO"
	    	    },
	    	    {
	    	    	"name":"impairment_label",
	    	    	"label":"Does the occupier have...",
	    	    	"type":"LABEL"
	    	    },
	    	    {
	    	    	"name":"visual_impairment",
	    	    	"label":"a Visual impairment?",
	    	    	"type":"YESNO"
	    	    },
	    	    {
	    	    	"name":"hearing_impairment",
	    	    	"label":"a Hearing impairment?",
	    	    	"type":"YESNO"
	    	    },
	    	    {
	    	    	"name":"other_impairment",
	    	    	"label":"any Other impairment?",
	    	    	"type":"YESNO"
	    	    },
	    	    {
	    	    	"name":"other_impairment_details",
	    	    	"label":"Details",
	    	    	"type":"TEXT"
	    	    }
	    	]
	    },
	    {
	    	"name":"firesafety_tutoring",
	    	"title":"Fire Safety Tutoring",
	    	"items":[
	    	    {
	    	    	"name":"history_of_fire",
	    	    	"label":"Is there evidence/history of fire?",
	    	    	"type":"YESNO"
	    	    },
	    	    {
	    	    	"name":"tutoring_required",
	    	    	"label":"Is fire safety tutoring required?",
	    	    	"type":"YESNO"
	    	    },
	    	    {
	    	    	"name":"youth_services_consent",
	    	    	"label":"Do the parent/guardian consent to being contacted by Youth Services?",
	    	    	"type":"YESNO"
	    	    },
	    	    {
	    	    	"name":"youthservices_notes",
	    	    	"label":"Details",
	    	    	"type":"TEXT"
	    	    }
	    	]
	    },
	    {
	    	"name":"additional_risks",
	    	"title":"Additional Operational Risks",
	    	"items":[
	    	    {
	    	    	"name":"dangerous_storage",
	    	    	"label":"Excessive or Dangerous storage?",
	    	    	"type":"YESNO"
	    	    },
	    	    {
	    	    	"name":"missing_doors",
	    	    	"label":"Missing internal doors?",
	    	    	"type":"YESNO"
	    	    },
	    	    {
	    	    	"name":"portable_heating",
	    	    	"label":"Portable heating (LPG/paraffin)?",
	    	    	"type":"YESNO"
	    	    },
	    	    {
	    	    	"name":"dangerous_animals",
	    	    	"label":"Dangerous Animals/Pets?",
	    	    	"type":"YESNO"
	    	    },
	    	    {
	    	    	"name":"medical_oxygen",
	    	    	"label":"Medical Oxygen?",
	    	    	"type":"YESNO"
	    	    },
	    	    {
	    	    	"name":"additional_risks_notes",
	    	    	"label":"Notes",
	    	    	"type":"TEXT"
	    	    }
	    	]
	    },
	    {
	    	"name":"safety_advice",
	    	"title":"Safety Advice/Planning",
	    	"items":[
	    	    {
	    	    	"name":"advice_night",
	    	    	"label":"Night time routine discussion",
	    	    	"type":"YESNO"
	    	    },
	    	    {
	    	    	"name":"advice_escape_plan",
	    	    	"label":"Escape Plan discussion",
	    	    	"type":"YESNO"
	    	    },
	    	    {
	    	    	"name":"advice_alarm_test",
	    	    	"label":"Smoke alarm tested",
	    	    	"type":"YESNO"
	    	    },
	    	    {
	    	    	"name":"advice_kitchen",
	    	    	"label":"Kitchen safety",
	    	    	"type":"YESNO"
	    	    },
	    	    {
	    	    	"name":"advice_electrical",
	    	    	"label":"Electrical safety",
	    	    	"type":"YESNO"
	    	    },
	    	    {
	    	    	"name":"advice_candle",
	    	    	"label":"Candle safety",
	    	    	"type":"YESNO"
	    	    },
	    	    {
	    	    	"name":"advice_smoking",
	    	    	"label":"Smoking safety",
	    	    	"type":"YESNO"
	    	    },
	    	    {
	    	    	"name":"advice_calling_fire",
	    	    	"label":"Calling the Fire Service",
	    	    	"type":"YESNO"
	    	    }
	    	]
	    },
	    {
	    	"name":"protection_equipment",
	    	"title":"Fire Protection Equipment",
	    	"items":[
	    	    {
	    	    	"name":"equipment_before_label",
	    	    	"label":"Before assessment",
	    	    	"type":"LABEL"
	    	    },
	    	    {
	    	    	"name":"alarms_correct_before",
	    	    	"label":"How many smoke alarms were working AND correctly sited?",
	    	    	"type":"NUMERIC"
	    	    },
	    	    {
	    	    	"name":"alarms_incorrect_before",
	    	    	"label":"How many smoke alarms were not working OR not sited correctly?",
	    	    	"type":"LABEL"
	    	    },
	    	    {
	    	    	"name":"equipment_after_label",
	    	    	"label":"After assessment",
	    	    	"type":"LABEL"
	    	    },
	    	    {
	    	    	"name":"alarms_correct_after",
	    	    	"label":"How many smoke alarms were fitted?",
	    	    	"type":"NUMERIC"
	    	    }
	    	]
	    }
	]
}